{
   "sversion" : "0.9",
   "type" : {
      "def" : {
         "hierarchical" : false,
         "inverse" : {
            "id" : "",
            "is_id" : true
         }
      },
      "meta" : {
         "attrs" : 97,
         "created" : "2019-12-16T10:00:27.802Z",
         "modified" : "2019-12-16T10:00:27.802Z",
         "name" : "UpStack",
         "nodeId" : "i:16",
         "path" : "/sys/types/relations",
         "superId" : "i:15",
         "type" : "relation_type",
         "ver" : "1.0"
      }
   }
}
