{
   "object" : {
      "def" : {
         "instance" : {
            "app" : "i:11",
            "down_port" : {
               "id" : "",
               "is_id" : true
            },
            "up_port" : {
               "id" : "",
               "is_id" : true
            }
         },
         "overrides" : null,
         "programs" : null
      },
      "meta" : {
         "attrs" : 31,
         "created" : "2019-11-13T21:01:37.671Z",
         "modified" : "2019-12-16T10:00:27.947Z",
         "name" : "stdIO",
         "nodeId" : "999:g:fe2b22a0-19ab-48de-a358-6dc7adc6e726",
         "path" : "/sys/host",
         "superId" : "3:i:1",
         "type" : "port",
         "ver" : "1.0"
      }
   },
   "sversion" : "0.9"
}
